mimetype_description/__init__.py
mimetype_description/freedesktop.org.xml
tests/__init__.py
tests/test_mimetype_description.py
mimetype_description-0.1.1.dist-info/LICENSE
mimetype_description-0.1.1.dist-info/METADATA
mimetype_description-0.1.1.dist-info/WHEEL
mimetype_description-0.1.1.dist-info/top_level.txt
mimetype_description-0.1.1.dist-info/RECORD
