Metadata-Version: 2.2
Name: mimetype-description
Version: 0.1.1
Summary: Human readable MIME type descriptions
Home-page: https://github.com/chesstrian/mimetype-description
Author: Christian Gutierrez
Author-email: chesstrian@gmail.com
License: MIT
Classifier: Development Status :: 4 - Beta
Classifier: Programming Language :: Python :: 3
Classifier: License :: OSI Approved :: MIT License
Classifier: Operating System :: OS Independent
Requires-Python: >=3.7
License-File: LICENSE
Dynamic: author
Dynamic: author-email
Dynamic: classifier
Dynamic: description
Dynamic: description-content-type
Dynamic: home-page
Dynamic: license
Dynamic: requires-python
Dynamic: summary
